self_unzip_html/__init__.py
self_unzip_html/crypto.py
self_unzip_html/minified_js.py
self_unzip_html/static_js.py
self_unzip_html/template.html
self_unzip_html-0.2.1.dist-info/LICENSE
self_unzip_html-0.2.1.dist-info/METADATA
self_unzip_html-0.2.1.dist-info/WHEEL
self_unzip_html-0.2.1.dist-info/entry_points.txt
self_unzip_html-0.2.1.dist-info/top_level.txt
self_unzip_html-0.2.1.dist-info/RECORD
