Metadata-Version: 2.1
Name: self-unzip-html
Version: 0.2.1
Summary: Create self-extracting and/or password protected HTML pages with arbitrary contents
Home-page: https://github.com/six-two/self-unzip.html
Author: six-two
Author-email: pip@six-two.dev
License: MIT License
Classifier: License :: OSI Approved :: MIT License
Classifier: Operating System :: POSIX :: Linux
Classifier: Programming Language :: Python :: 3
Classifier: Programming Language :: Python :: 3.9
Classifier: Programming Language :: Python :: 3.10
Requires-Python: >=3.9
License-File: LICENSE
